AUTHORS.rst
CONTRIBUTING.rst
HISTORY.rst
MANIFEST.in
README.rst
requirements.txt
setup.py
Solution_Dates.egg-info/SOURCES.txt
Solution_dates.egg-info/PKG-INFO
Solution_dates.egg-info/SOURCES.txt
Solution_dates.egg-info/dependency_links.txt
Solution_dates.egg-info/not-zip-safe
Solution_dates.egg-info/requires.txt
Solution_dates.egg-info/top_level.txt
solution_dates/__init__.py
solution_dates/parser.py
solution_dates/fields/__init__.py
solution_dates/fields/date.py
tests/__init__.py
tests/test_fields.py
tests/test_parser.py